Metadata-Version: 2.1
Name: lagrange-interpolation
Version: 0.1.0
Summary: My implementation of Lagrange interpolation
Home-page: https://github.com/shuds13/pyexample
Author: Taylor Swift
Author-email: wdywbac@gmail.com
License: BSD 2-clause
Platform: UNKNOWN
Classifier: Development Status :: 1 - Planning
Classifier: Intended Audience :: Science/Research
Classifier: License :: OSI Approved :: BSD License
Classifier: Operating System :: POSIX :: Linux
Classifier: Programming Language :: Python :: 2
Classifier: Programming Language :: Python :: 2.7
Classifier: Programming Language :: Python :: 3
Classifier: Programming Language :: Python :: 3.4
Classifier: Programming Language :: Python :: 3.5
